pytest_automock/__init__.py
pytest_automock/mock.py
pytest_automock/plugin.py
pytest_automock-0.9.1.dist-info/METADATA
pytest_automock-0.9.1.dist-info/WHEEL
pytest_automock-0.9.1.dist-info/entry_points.txt
pytest_automock-0.9.1.dist-info/top_level.txt
pytest_automock-0.9.1.dist-info/RECORD
