Metadata-Version: 2.1
Name: pytest-automock
Version: 0.9.1
Summary: Pytest plugin for automatical mocks creation
Home-page: https://github.com/pohmelie/pytest-automock
License: UNKNOWN
Platform: UNKNOWN
Requires-Python: >=3.6
Provides-Extra: dev
Requires-Dist: flake8 ; extra == 'dev'
Requires-Dist: pytest ; extra == 'dev'
Requires-Dist: pytest-asyncio ; extra == 'dev'
Requires-Dist: pytest-cov ; extra == 'dev'
